Metadata-Version: 2.1
Name: django-configurations-celery
Version: 2020.7.1
Summary: django-configurations Celery settings
Home-page: https://github.com/andrewp-as-is/django-configurations-celery.py
License: Unlicense
Keywords: django django-configurations celery
Platform: UNKNOWN
Classifier: Framework :: Django
Classifier: License :: Public Domain
Classifier: Operating System :: OS Independent
Classifier: Programming Language :: Python :: 3
